MANIFEST.in
README.rst
requirements.txt
setup.py
./autoflow/__init__.py
./autoflow/__version__.py
./autoflow/constants.py
./autoflow/data_process/__init__.py
./autoflow/data_process/abnormal/__init__.py
./autoflow/data_process/balance/__init__.py
./autoflow/data_process/impute/__init__.py
./autoflow/data_process/impute/delete_nan.py
./autoflow/ensemble/__init__.py
./autoflow/ensemble/base.py
./autoflow/ensemble/trained_data_fetcher.py
./autoflow/ensemble/trials_fetcher.py
./autoflow/ensemble/utils.py
./autoflow/ensemble/mean/__init__.py
./autoflow/ensemble/mean/regressor.py
./autoflow/ensemble/stack/__init__.py
./autoflow/ensemble/stack/base.py
./autoflow/ensemble/stack/classifier.py
./autoflow/ensemble/stack/regressor.py
./autoflow/ensemble/vote/__init__.py
./autoflow/ensemble/vote/classifier.py
./autoflow/estimator/__init__.py
./autoflow/estimator/base.py
./autoflow/estimator/classifier.py
./autoflow/estimator/regressor.py
./autoflow/estimator/transformer.py
./autoflow/evaluation/__init__.py
./autoflow/evaluation/base.py
./autoflow/evaluation/ensemble_evaluator.py
./autoflow/evaluation/train_evaluator.py
./autoflow/feature_engineer/__init__.py
./autoflow/feature_engineer/compress/__init__.py
./autoflow/feature_engineer/compress/f1_score.py
./autoflow/feature_engineer/compress/pearson.py
./autoflow/feature_engineer/compress/similarity_base.py
./autoflow/feature_engineer/compress/variance.py
./autoflow/feature_engineer/encode/__init__.py
./autoflow/feature_engineer/encode/label_encode.py
./autoflow/feature_engineer/operate/__init__.py
./autoflow/feature_engineer/operate/drop_all.py
./autoflow/feature_engineer/transform/__init__.py
./autoflow/feature_engineer/transform/guassion_tranform.py
./autoflow/hdl/__init__.py
./autoflow/hdl/hdl_bank.json
./autoflow/hdl/hdl_constructor.py
./autoflow/hdl/utils.py
./autoflow/hdl/smac/__init__.py
./autoflow/hdl2shps/__init__.py
./autoflow/hdl2shps/hdl2shps.py
./autoflow/manager/__init__.py
./autoflow/manager/data_manager.py
auto_flow.egg-info/PKG-INFO
auto_flow.egg-info/SOURCES.txt
auto_flow.egg-info/dependency_links.txt
auto_flow.egg-info/requires.txt
auto_flow.egg-info/top_level.txt
