Metadata-Version: 2.1
Name: auto-flow
Version: 0.1.1
Summary: AutoFlow: Automatic machine learning workflow modeling platform.
Home-page: https://github.com/auto-flow/autoflow
Author: qichun tang
Author-email: tqichun@gmail.com
License: BSD
Platform: Linux
Classifier: Environment :: Console
Classifier: Intended Audience :: Developers
Classifier: Intended Audience :: Education
Classifier: Intended Audience :: Science/Research
Classifier: Intended Audience :: Information Technology
Classifier: License :: OSI Approved :: BSD License
Classifier: Natural Language :: English
Classifier: Operating System :: OS Independent
Classifier: Topic :: Scientific/Engineering :: Artificial Intelligence
Classifier: Topic :: Scientific/Engineering :: Information Analysis
Classifier: Programming Language :: Python :: 3.6
Classifier: Programming Language :: Python :: 3.7
Requires-Python: >=3.6.*
